{"layout":{"pages":[{"id":"page_cfqhvmtu","title":"General","sections":[{"id":"section_djgdat86","fields":[{"id":"groupsRelationships","state":{"visible":true,"read-only":false},"display":"objectField","signpostPosition":"right-middle"}]}]}]},"schema":{"groupsRelationships":{"type":{"dataType":"complex","isMultiple":false,"fields":[{"type":{"dataType":"string","isMultiple":true},"label":"vmIDs","id":"vmIDs","constraints":{}},{"type":{"dataType":"string","isMultiple":false},"label":"projectID","id":"projectID","constraints":{}}]},"label":"groupsRelationships","id":"groupsRelationships","constraints":{"required":false}}},"options":{"externalValidations":[]},"itemId":""}